python_can_csscan_mux/CSSCANMux.py
python_can_csscan_mux/CSSCANMuxBus.py
python_can_csscan_mux/CSSCANMuxReader.py
python_can_csscan_mux/Common.py
python_can_csscan_mux/ISO_TP.py
python_can_csscan_mux/Message.py
python_can_csscan_mux/Timeout.py
python_can_csscan_mux/__init__.py
python_can_csscan_mux-24.10.30.dist-info/METADATA
python_can_csscan_mux-24.10.30.dist-info/WHEEL
python_can_csscan_mux-24.10.30.dist-info/entry_points.txt
python_can_csscan_mux-24.10.30.dist-info/licenses/LICENSE
python_can_csscan_mux-24.10.30.dist-info/RECORD
