Metadata-Version: 2.3
Name: python-can-csscan-mux
Version: 24.10.30
Summary: Mux/demux data from the CSS Electronics' CANmod.router device through Python
Project-URL: Homepage, https://canlogger.csselectronics.com/tools-docs/csscan_mux/python_csscan/
Author: CSS Electronics
Author-email: contact@csselectronics.com
License: MIT
License-File: LICENSE
Classifier: License :: OSI Approved :: MIT License
Classifier: Operating System :: OS Independent
Classifier: Programming Language :: Python :: 3
Requires-Python: >=3.7
Requires-Dist: dataclasses-json>=0.6.0
Requires-Dist: python-can>=4.0.0
